hopsworks/__init__.py
hopsworks/command.py
hopsworks/connection.py
hopsworks/constants.py
hopsworks/decorators.py
hopsworks/environment.py
hopsworks/execution.py
hopsworks/flink_cluster.py
hopsworks/git_commit.py
hopsworks/git_file_status.py
hopsworks/git_op_execution.py
hopsworks/git_provider.py
hopsworks/git_remote.py
hopsworks/git_repo.py
hopsworks/job.py
hopsworks/job_schedule.py
hopsworks/kafka_schema.py
hopsworks/kafka_topic.py
hopsworks/library.py
hopsworks/project.py
hopsworks/secret.py
hopsworks/user.py
hopsworks/util.py
hopsworks/version.py
hopsworks/client/__init__.py
hopsworks/client/auth.py
hopsworks/client/base.py
hopsworks/client/exceptions.py
hopsworks/client/external.py
hopsworks/client/hopsworks.py
hopsworks/core/__init__.py
hopsworks/core/alerts_api.py
hopsworks/core/dataset_api.py
hopsworks/core/environment_api.py
hopsworks/core/execution_api.py
hopsworks/core/flink_cluster_api.py
hopsworks/core/git_api.py
hopsworks/core/git_op_execution_api.py
hopsworks/core/git_provider_api.py
hopsworks/core/git_remote_api.py
hopsworks/core/job_api.py
hopsworks/core/kafka_api.py
hopsworks/core/library_api.py
hopsworks/core/opensearch_api.py
hopsworks/core/project_api.py
hopsworks/core/search_api.py
hopsworks/core/secret_api.py
hopsworks/core/variable_api.py
hopsworks/engine/__init__.py
hopsworks/engine/environment_engine.py
hopsworks/engine/execution_engine.py
hopsworks/engine/git_engine.py
hopsworks/internal/__init__.py
hopsworks/internal/aliases.py
hopsworks/mcp/__init__.py
hopsworks/mcp/main.py
hopsworks/mcp/server.py
hopsworks/mcp/models/__init__.py
hopsworks/mcp/models/dataset.py
hopsworks/mcp/models/feature_group.py
hopsworks/mcp/models/feature_store.py
hopsworks/mcp/models/job.py
hopsworks/mcp/models/project.py
hopsworks/mcp/prompts/__init__.py
hopsworks/mcp/prompts/project.py
hopsworks/mcp/prompts/system.py
hopsworks/mcp/resources/__init__.py
hopsworks/mcp/resources/feature_store.py
hopsworks/mcp/resources/project.py
hopsworks/mcp/tools/__init__.py
hopsworks-4.6.1.dist-info/licenses/LICENSE
hopsworks-4.6.1.dist-info/METADATA
hopsworks-4.6.1.dist-info/WHEEL
hopsworks-4.6.1.dist-info/entry_points.txt
hopsworks-4.6.1.dist-info/top_level.txt
hopsworks-4.6.1.dist-info/RECORD
